rhsolpy/__init__.py
rhsolpy/rankine_hugoniot.py
rhsolpy-1.0.0a2.dist-info/LICENSE
rhsolpy-1.0.0a2.dist-info/METADATA
rhsolpy-1.0.0a2.dist-info/WHEEL
rhsolpy-1.0.0a2.dist-info/top_level.txt
rhsolpy-1.0.0a2.dist-info/RECORD
