Metadata-Version: 2.1
Name: rhsolpy
Version: 1.0.0a2
Summary: rhsolpy: Rankine-Hugoniot relation solver for anisotropic plasmas
Home-page: https://github.com/kx198x/rhsolpy
Author: Katsuaki Higashimori
Author-email: k.higashimori@gmail.com
Maintainer: Katsuaki Higashimori
Maintainer-email: k.higashimori@gmail.com
License: BSD 3-Clause
Download-URL: https://github.com/kx198x/rhsolpy
Platform: UNKNOWN
Requires-Python: >=3.7
